.travis.yml
AUTHORS
ChangeLog
LICENSE
README.rst
setup.cfg
setup.py
saga/__init__.py
saga/saga.py
saga/saga_test.py
saga_py.egg-info/PKG-INFO
saga_py.egg-info/SOURCES.txt
saga_py.egg-info/dependency_links.txt
saga_py.egg-info/not-zip-safe
saga_py.egg-info/pbr.json
saga_py.egg-info/top_level.txt