Metadata-Version: 1.1
Name: saga-py
Version: 1.1.0
Summary: create a series of dependent actions and roll everything back when one of them fails
Home-page: https://github.com/flowpl/dbit
Author: Florian Plattner
Author-email: me@florianplattner.de
License: MIT
Keywords: saga
Platform: UNKNOWN
Classifier: Development Status :: 5 - Production/Stable
Classifier: Environment :: Other Environment
Classifier: Intended Audience :: Developers
Classifier: Intended Audience :: Information Technology
Classifier: License :: OSI Approved :: MIT License
Classifier: Operating System :: OS Independent
Classifier: Programming Language :: Python :: 3.5
Classifier: Programming Language :: Python :: 3.6
Classifier: Topic :: Software Development :: Libraries :: Python Modules
